quranallsbuforuni/__init__.py
quranallsbuforuni/module1.py
quranallsbuforuni/module2.py
Quransureh1-1.dist-info/METADATA
Quransureh1-1.dist-info/WHEEL
Quransureh1-1.dist-info/top_level.txt
Quransureh1-1.dist-info/RECORD
