Metadata-Version: 2.1
Name: Quransureh1
Version: 1
Summary: Quransureh1
Author: Masoud Shafiei
Author-email: masoudshafiei89@yahoo.com
Keywords: quran,sureh1
Classifier: Programming Language :: Python :: 3
